deep_river/__init__.py
deep_river/__version__.py
deep_river/base.py
deep_river/anomaly/__init__.py
deep_river/anomaly/ae.py
deep_river/anomaly/probability_weighted_ae.py
deep_river/anomaly/rolling_ae.py
deep_river/anomaly/scaler.py
deep_river/classification/__init__.py
deep_river/classification/classifier.py
deep_river/classification/rolling_classifier.py
deep_river/classification/zoo.py
deep_river/regression/__init__.py
deep_river/regression/multioutput.py
deep_river/regression/regressor.py
deep_river/regression/rolling_regressor.py
deep_river/regression/zoo.py
deep_river/utils/__init__.py
deep_river/utils/estimator_checks.py
deep_river/utils/hooks.py
deep_river/utils/inspect.py
deep_river/utils/params.py
deep_river/utils/tensor_conversion.py
deep_river/utils/test_estimators.py
deep_river/utils/test_tensor_conversion.py
deep_river-0.3.2.dist-info/licenses/LICENSE
deep_river-0.3.2.dist-info/METADATA
deep_river-0.3.2.dist-info/WHEEL
deep_river-0.3.2.dist-info/top_level.txt
deep_river-0.3.2.dist-info/RECORD
