Metadata-Version: 2.4
Name: deep_river
Version: 0.3.2
Summary: Online Deep Learning for river
Author-email: Cedric Kulbach <cedric.kulbach@googlemail.com>, Lucas Cazzonelli <Cazzonelli@fzi.de>, Hoang-Anh Ngo <hoang-anh.ngo@alumni.polytechnique.org>, Max Halford <maxhalford25@gmail.com>, Saulo Martiello Mastelini <saulomastelini@gmail.com>
License: BSD-3-Clause
Project-URL: Homepage, https://github.com/online-ml/deep-river
Project-URL: Repository, https://github.com/online-ml/deep-river
Project-URL: Documentation, https://github.com/online-ml/deep-river
Keywords: online-learning,deep-learning,data-streams
Classifier: Programming Language :: Python
Classifier: Programming Language :: Python :: 3
Classifier: Programming Language :: Python :: 3.10
Classifier: Programming Language :: Python :: 3.11
Classifier: Programming Language :: Python :: 3.12
Classifier: Programming Language :: Python :: Implementation :: CPython
Classifier: Programming Language :: Python :: Implementation :: PyPy
Requires-Python: <3.13,>=3.10
License-File: LICENSE
Requires-Dist: scikit-learn~=1.5.0
Requires-Dist: torch==2.2.2
Requires-Dist: pandas~=2.2.2
Requires-Dist: numpy~=1.26.4
Requires-Dist: river
Requires-Dist: tqdm~=4.66.5
Requires-Dist: torchviz~=0.0.2
Requires-Dist: mkdocstrings[python]>=0.19.0
Requires-Dist: pytkdocs[numpy-style]>=0.5.0
Requires-Dist: sortedcontainers>=2.4.0
Provides-Extra: dev
Requires-Dist: graphviz>=0.20.3; extra == "dev"
Requires-Dist: matplotlib>=3.9.2; extra == "dev"
Requires-Dist: mypy>=1.11.1; extra == "dev"
Requires-Dist: codecov>=2.1.13; extra == "dev"
Requires-Dist: pre-commit>=3.8.0; extra == "dev"
Requires-Dist: pytest>=8.3.2; extra == "dev"
Requires-Dist: pytest-cov>=5.0.0; extra == "dev"
Requires-Dist: black>=24.8.0; extra == "dev"
Requires-Dist: flake8>=7.1.1; extra == "dev"
Requires-Dist: isort>=5.13.2; extra == "dev"
Requires-Dist: jupyter>=1.0.0; extra == "dev"
Requires-Dist: pyupgrade==3.17.0; extra == "dev"
Requires-Dist: flask>=3.0.2; extra == "dev"
Requires-Dist: ipykernel>=6.9.0; extra == "dev"
Requires-Dist: mike>=0.5.3; extra == "dev"
Requires-Dist: mkdocs>=1.2.3; extra == "dev"
Requires-Dist: mkdocs-awesome-pages-plugin>=2.7.0; extra == "dev"
Requires-Dist: mkdocs-gen-files>=0.3.5; extra == "dev"
Requires-Dist: mkdocs-charts-plugin>=0.0.8; extra == "dev"
Requires-Dist: mkdocs-literate-nav>=0.4.1; extra == "dev"
Requires-Dist: mkdocs-material>=8.1.11; extra == "dev"
Requires-Dist: ipython_genutils>=0.1.0; extra == "dev"
Requires-Dist: mkdocs-jupyter>=0.20.0; extra == "dev"
Requires-Dist: nbconvert>=6.4.2; extra == "dev"
Requires-Dist: jupyter_contrib_nbextensions==0.7.0; extra == "dev"
Requires-Dist: numpydoc>=1.2; extra == "dev"
Requires-Dist: notebook==6.4.3; extra == "dev"
Requires-Dist: spacy>=3.2.2; extra == "dev"
Requires-Dist: jinja2>=3.0.3; extra == "dev"
Requires-Dist: dominate; extra == "dev"
Requires-Dist: jupyter-client; extra == "dev"
Requires-Dist: python-slugify; extra == "dev"
Requires-Dist: watermark==2.3.1; extra == "dev"
Requires-Dist: plotly>=5.0.0; extra == "dev"
Dynamic: license-file
